{"artwork":null,"bars":20,"bpm":88,"collaborative":false,"color":"#fd7d23","created":"2025-10-30 06:28:08.981000","deleted":false,"description":"","gadget-details":[{"beats":16,"color":"#2f9aef","created":"2025-10-30 06:29:15.860000","deleted":false,"description":"","id":873957,"idata":{"author":"Anonymous","cloned":false,"displayOrder":2,"editor-theme":"tunepad-dark","gain":1.1594424377547368,"hasError":false,"midi-input":false,"midi-output":false,"minimized":false,"pan":0,"patchId":1,"python":"# 🎸 Bass – follows root notes of each chord\n# Lower octave for depth and darker tone\n\nfor note in [24, 28, 31, 24]:  # C2 → E2 → G2 → C2 (1 octave lower)\n    playNote(note, beats=4)\n\n\n\n\n","show-editor":true,"show-instrument":true,"show-notation":true,"show-output":false,"show-timeline":true},"instrument":"bass","modified":"2025-10-30 06:59:06.449000","name":"New Bass 1","public":false,"remix_parent":null,"version":"2.0","voice":"piano"},{"beats":12,"color":"#2f9aef","created":"2025-10-30 06:29:34.759000","deleted":false,"description":"","id":873958,"idata":{"author":"Anonymous","cloned":false,"displayOrder":3,"editor-theme":"tunepad-dark","gain":0.9952123020372664,"hasError":false,"midi-input":false,"midi-output":false,"minimized":false,"pan":0,"patchId":11,"python":"# 🥁 Drums – soft ambient groove (88 BPM)\n# Kick = 36, Snare = 38, Hi-hat = 42\n\nfor i in range(8):\n    playNote(42, beats=1)      # hi-hat every beat\n    if i % 4 == 0:\n        playNote(36, beats=0.5)  # kick on beat 1\n    if i % 8 == 2:\n        playNote(38, beats=0.5)  # snare on beat 3\n\n# Drum rhythm created using modulo operator for timing\n# Example logic adapted from Van Schooneveld (n.d.), Real Python:\n# https://realpython.com/python-modulo-operator/\n\n","show-editor":true,"show-instrument":true,"show-notation":true,"show-output":false,"show-timeline":true},"instrument":"drums","modified":"2025-11-03 11:17:08.764000","name":"New Drums","public":false,"remix_parent":null,"version":"2.0","voice":"piano"},{"beats":96,"color":"#2f9aef","created":"2025-10-30 06:31:39.387000","deleted":false,"description":"","id":873959,"idata":{"author":"Anonymous","cloned":false,"displayOrder":1,"editor-theme":"tunepad-dark","gain":1.5921948325733395,"hasError":false,"midi-input":false,"midi-output":false,"minimized":false,"pan":0,"patchId":9,"python":"# 🎹 Radiohead – All I Need (Instrumental to Outro)\n# Keyboard / Chord layer (no wait(), just natural overlap)\n\n# Chord 1: C major (C–E–G)\nplayNote(48, beats=4)\nplayNote(52, beats=4)\nplayNote(55, beats=4)\n# Repeat for sustain\nplayNote(48, beats=4)\nplayNote(52, beats=4)\nplayNote(55, beats=4)\n\n# Chord 2: E minor (E–G–B)\nplayNote(52, beats=4)\nplayNote(55, beats=4)\nplayNote(59, beats=4)\nplayNote(52, beats=4)\nplayNote(55, beats=4)\nplayNote(59, beats=4)\n\n# Chord 3: G major (G–B–D)\nplayNote(55, beats=4)\nplayNote(59, beats=4)\nplayNote(62, beats=4)\nplayNote(55, beats=4)\nplayNote(59, beats=4)\nplayNote(62, beats=4)\n\n# Chord 4: C major (resolve)\nplayNote(48, beats=4)\nplayNote(52, beats=4)\nplayNote(55, beats=4)\nplayNote(48, beats=4)\nplayNote(52, beats=4)\nplayNote(55, beats=4)\n\n# Built using TunePad's playNote() function\n# Reference: TunePad (n.d.). Learn TunePad tutorials. https://tunepad.com\n","show-editor":true,"show-instrument":true,"show-notation":true,"show-output":false,"show-timeline":true},"instrument":"piano","modified":"2025-11-03 11:18:02.446000","name":"New Keyboard","public":false,"remix_parent":null,"version":"2.0","voice":"piano"},{"beats":24,"color":"#2f9aef","created":"2025-10-30 06:56:57.153000","deleted":false,"description":"","id":873962,"idata":{"author":"Anonymous","cloned":false,"displayOrder":4,"editor-theme":"tunepad-dark","gain":0.8595586804729739,"hasError":false,"midi-input":false,"midi-output":false,"minimized":false,"pan":0,"patchId":9,"python":"# 🎹 Radiohead – All I Need (Lead / Melody line)\n# Instrument: Keyboard (Piano)\n# This creates the emotional floating melody that sits on top of the chords.\n\n# Section 1 – gentle lift over C → Em\n# Higher octave (C5–E5 range) for an airy tone\nplayNote(60, beats=2)   # C5\nplayNote(62, beats=2)   # D5\nplayNote(64, beats=2)   # E5\nplayNote(62, beats=2)   # D5\nplayNote(60, beats=4)   # Hold C5 (soft resolve)\n\n# Section 2 – expressive variation over G → C\n# Mimics the feel of the vocals\nplayNote(76, beats=2)   # E5\nplayNote(79, beats=2)   # G5\nplayNote(77, beats=2)   # F5\nplayNote(76, beats=2)   # E5\nplayNote(72, beats=4)   # Final C5 – resolves to tonic\n\n# Simple repeating melody built from MIDI note values\n# Experimented with timing using for loops and beats for emotional pacing\n# Reference: Horn, West, & Roberts (2022). *Learning Music with Code.* MIT Press.\n\n","show-editor":true,"show-instrument":true,"show-notation":true,"show-output":false,"show-timeline":true},"instrument":"piano","modified":"2025-11-03 11:16:52.982000","name":"Melody","public":false,"remix_parent":null,"version":"2.0","voice":"piano"}],"id":117860,"import_export_version":1,"meter":"4/4","modified":"2025-11-02 11:06:24.358000","name":"all i need - code prototype","preview":null,"pucks":{"daw-zoom-factor":0.5,"key":"C major","owner_id":"d598c228-3421-45e9-b9cd-64142f073bc0"},"remix_parent":null,"summary":"","tags":[],"tracks":[{"clips":[{"beats":96,"color":"blue","end":96,"start":0,"trim":0,"waveform":false}],"color":"blue","gadget_id":873959,"gain":4.039924201880348,"hidden":false,"id":873959,"mute":false,"name":"New Keyboard","order":0,"pan":0,"solo":false,"solo-mute":false},{"clips":[{"beats":16,"color":"magenta","end":16,"start":0,"trim":0,"waveform":false},{"beats":16,"color":"magenta","end":32,"start":16,"trim":0,"waveform":false}],"color":"magenta","gadget_id":873957,"gain":1.2849838462670324,"hidden":false,"id":873957,"mute":false,"name":"New Bass 1","order":1,"pan":0,"solo":false,"solo-mute":false},{"clips":[{"beats":12,"color":"green","end":12,"start":0,"trim":0,"waveform":false},{"beats":12,"color":"green","end":24,"start":12,"trim":0,"waveform":false},{"beats":12,"color":"green","end":36,"start":24,"trim":0,"waveform":false}],"color":"green","gadget_id":873958,"gain":-0.04168528421706709,"hidden":false,"id":873958,"mute":false,"name":"New Drums","order":2,"pan":0,"solo":false,"solo-mute":false},{"clips":[{"beats":24,"color":"blue","end":24,"start":0,"trim":0,"waveform":false},{"beats":24,"color":"blue","end":48,"start":24,"trim":0,"waveform":false}],"color":"blue","gadget_id":873962,"gain":-1.3144893897609164,"hidden":false,"id":873962,"mute":false,"name":"New Keyboard 1","order":3,"pan":0,"solo":false,"solo-mute":false}],"user_id":"d598c228-3421-45e9-b9cd-64142f073bc0","username":"medha","visibility":"private"}